Metadata-Version: 1.0
Name: probabilipy
Version: 1.0
Summary: Probability distributions analysis package
Home-page: UNKNOWN
Author: UNKNOWN
Author-email: UNKNOWN
License: UNKNOWN
Platform: UNKNOWN
